<TruckAddon>
	<PhysicsModel AcceptVisualDamage="false" Mesh="trucks/tuning/cotco_canyon_tuning" MeshFrame="cotco_canyon_roofrack_slot_02_fuel">	
		<Body Collisions="None" Mass="20" ModelFrame="BoneAddon_cdt">
			<Constraint Type="Rigid"/>
			<Body Collisions="None" Mass="20" ModelFrame="BoneRoofRack01Slot02_cdt">
				<Constraint
					Type="Fixed"
					LinearLimitsX="(-0.005;0.005)"
					LinearLimitsY="(0;0)"
					LinearLimitsZ="(-0.005;0.005)"
				>
					<Motor Damping="10" Spring="15" Type="Spring" />
				</Constraint>
			</Body>
		</Body>
	</PhysicsModel>
	
	<TruckData FuelCapacity="15" />
 	<FuelHide>
		<Mesh Frame="cotco_canyon_roofrack_slot_02_fuel" HideThreshold="0.0" />
	</FuelHide>
	
	<GameData
		CameraPreset="supplies_roof"
		Category="top"
		IsConsumable="true"
		IsCustomizable="false"
		Price="200"
		UnlockByExploration="false"
		UnlockByRank="1"
	>
		<UiDesc
			UiDesc="UI_TUNING_ROOFRACK_FUEL_DESC"
			UiIcon30x30=""
			UiIcon40x40=""
			UiName="UI_TUNING_ROOFRACK_FUEL_NAME"
		/>
		<RequiredAddon Types="cotco_canyon_roofrack_01" />
		<InstallSocket Type="CotcoCanyonRoofrackSlot02" />
	</GameData>
</TruckAddon>
